include/SHARPlib/algorithms.h
include/SHARPlib/constants.h
include/SHARPlib/interp.h
include/SHARPlib/layer.h
include/SHARPlib/params/convective.h
include/SHARPlib/params/fire.h
include/SHARPlib/params/winter.h
include/SHARPlib/parcel.h
include/SHARPlib/thermo.h
include/SHARPlib/version.h.in
include/SHARPlib/winds.h
lib/cmake/SHARPlib/SHARPlibConfig.cmake
lib/cmake/SHARPlib/SHARPlibConfigVersion.cmake
lib/cmake/SHARPlib/SHARPlibTargets-release.cmake
lib/cmake/SHARPlib/SHARPlibTargets.cmake
lib/SHARPlib.lib
nwsspc/sharp/calc/__init__.pyi
nwsspc/sharp/calc/constants.pyi
nwsspc/sharp/calc/interp.pyi
nwsspc/sharp/calc/layer.pyi
nwsspc/sharp/calc/params.pyi
nwsspc/sharp/calc/parcel.pyi
nwsspc/sharp/calc/thermo.pyi
nwsspc/sharp/calc/winds.pyi
nwsspc/sharp/calc.cp314t-win_amd64.pyd
nwsspc/sharp/py.typed
sharplib-1.2.1.post1.dist-info/METADATA
sharplib-1.2.1.post1.dist-info/WHEEL
sharplib-1.2.1.post1.dist-info/licenses/LICENSE
sharplib-1.2.1.post1.dist-info/RECORD
