Metadata-Version: 2.2
Name: SHARPlib
Version: 1.2.1.post1
Summary: Sounding and Hodograph Analysis and Research Program Library (SHARPlib) for processing vertical profiles of meteorological/atmospheric sounding data.
Keywords: meteorology,weather,atmospheric science,atmosphere,soundings,skewt,hodograph
Author-Email: Kelton Halbert <kelton.halbert@noaa.gov>
Classifier: Development Status :: 4 - Beta
Classifier: Programming Language :: Python :: 3 :: Only
Classifier: Programming Language :: Python :: 3.10
Classifier: Programming Language :: Python :: 3.11
Classifier: Programming Language :: Python :: 3.12
Classifier: Programming Language :: Python :: 3.13
Classifier: Programming Language :: Python :: 3.14
Classifier: Topic :: Scientific/Engineering
Classifier: Topic :: Scientific/Engineering :: Atmospheric Science
Classifier: Intended Audience :: Science/Research
Classifier: Operating System :: OS Independent
Project-URL: homepage, https://github.com/keltonhalbert/SHARPlib
Project-URL: Documentation, https://keltonhalbert.github.io/SHARPlib
Project-URL: Bluesky, https://bsky.app/profile/stormscale.io
Requires-Python: >=3.10
Requires-Dist: numpy>=2.0.0
Provides-Extra: test
Requires-Dist: pytest; extra == "test"
Requires-Dist: pandas; extra == "test"
Requires-Dist: fastparquet; extra == "test"
